sfreeze/__init__.py
sfreeze/freeze.py
sfreeze-0.0.2.dist-info/METADATA
sfreeze-0.0.2.dist-info/WHEEL
sfreeze-0.0.2.dist-info/top_level.txt
sfreeze-0.0.2.dist-info/RECORD
