Metadata-Version: 2.1
Name: sfreeze
Version: 0.0.2
Summary: A python tool for freezing objects in AWS S3
Home-page: https://github.com/Jlrine2/sfreeze
License: BSD
Platform: UNKNOWN
Classifier: License :: OSI Approved :: BSD License
Classifier: Natural Language :: English
Classifier: Programming Language :: Python :: 3
Classifier: Programming Language :: Python :: 3.8
Classifier: Programming Language :: Python :: 3.9
Requires-Python: ~=3.8
Requires-Dist: boto3
